LICENSE
setup.py
django_dynsettings_ritual.egg-info/PKG-INFO
django_dynsettings_ritual.egg-info/SOURCES.txt
django_dynsettings_ritual.egg-info/dependency_links.txt
django_dynsettings_ritual.egg-info/requires.txt
django_dynsettings_ritual.egg-info/top_level.txt
grimoire/django/dynsettings/__init__.py
grimoire/django/dynsettings/admin.py
grimoire/django/dynsettings/apps.py
grimoire/django/dynsettings/models.py
grimoire/django/dynsettings/utils.py
grimoire/django/dynsettings/locale/es/LC_MESSAGES/django.po
grimoire/django/dynsettings/migrations/0001_initial.py
grimoire/django/dynsettings/migrations/0002_auto_20150421_2247.py
grimoire/django/dynsettings/migrations/0003_auto_20170910_0012.py
grimoire/django/dynsettings/migrations/0004_auto_20200319_0007.py
grimoire/django/dynsettings/migrations/0005_alter_booleandynamicsetting_value_and_more.py
grimoire/django/dynsettings/migrations/0006_alter_jsondynamicsetting_value.py
grimoire/django/dynsettings/migrations/__init__.py