Metadata-Version: 2.1
Name: django-dynsettings-ritual
Version: 1.1.1
Summary: A Django application used to store dynamic settings (i.e. settings beyond the settings.py file), and retrieve them via another special object (instead of django.conf.settings, and wrapping it).
Home-page: https://github.com/luismasuelli/django-dynsettings-ritual
Author: Luis y Anita
Author-email: luismasuelli@hotmail.com
License: LGPL
License-File: LICENSE
